[{"id":70335,"version":null,"year":1961,"countryCode":165,"countryName":"Pakistan","shortName":"Pakistan","isoa2":"PK","record":"BiocapPerCap","cropLand":0.292641089252019,"grazingLand":0.0160223631584894,"forestLand":0.0296459738530093,"fishingGround":0.147514168941012,"builtupLand":0.0102046314858599,"carbon":0.0,"value":0.496028226690389,"score":"3A"},{"id":70347,"version":null,"year":1962,"countryCode":165,"countryName":"Pakistan","shortName":"Pakistan","isoa2":"PK","record":"BiocapPerCap","cropLand":0.294356101292377,"grazingLand":0.0155999587101666,"forestLand":0.0289453048677063,"fishingGround":0.14362518948555,"builtupLand":0.0104801845684241,"carbon":0.0,"value":0.493006738924223,"score":"3A"},{"id":70359,"version":null,"year":1963,"countryCode":165,"countryName":"Pakistan","shortName":"Pakistan","isoa2":"PK","record":"BiocapPerCap","cropLand":0.308150657763184,"grazingLand":0.0151642296550122,"forestLand":0.0304070191042945,"fishingGround":0.139613533475836,"builtupLand":0.0112338278166096,"carbon":0.0,"value":0.504569267814937,"score":"3A"},{"id":70371,"version":null,"year":1964,"countryCode":165,"countryName":"Pakistan","shortName":"Pakistan","isoa2":"PK","record":"BiocapPerCap","cropLand":0.29497765397605,"grazingLand":0.0147521585153004,"forestLand":0.0325773294734075,"fishingGround":0.135819690388031,"builtupLand":0.0108631361919987,"carbon":0.0,"value":0.488989968544787,"score":"3A"},{"id":70383,"version":null,"year":1965,"countryCode":165,"countryName":"Pakistan","shortName":"Pakistan","isoa2":"PK","record":"BiocapPerCap","cropLand":0.299323778404717,"grazingLand":0.0143255769127932,"forestLand":0.033537536384895,"fishingGround":0.131892252846082,"builtupLand":0.0110020404955561,"carbon":0.0,"value":0.490081185044043,"score":"3A"},{"id":70395,"version":null,"year":1966,"countryCode":165,"countryName":"Pakistan","shortName":"Pakistan","isoa2":"PK","record":"BiocapPerCap","cropLand":0.281053311966713,"grazingLand":0.0139514056038407,"forestLand":0.0327304203297974,"fishingGround":0.128447344680182,"builtupLand":0.0105451129899241,"carbon":0.0,"value":0.466727595570457,"score":"3A"},{"id":70407,"version":null,"year":1967,"countryCode":165,"countryName":"Pakistan","shortName":"Pakistan","isoa2":"PK","record":"BiocapPerCap","cropLand":0.315949330029853,"grazingLand":0.0135473965634284,"forestLand":0.0349057389816167,"fishingGround":0.124727727464447,"builtupLand":0.0121517396962331,"carbon":0.0,"value":0.501281932735579,"score":"3A"},{"id":70419,"version":null,"year":1968,"countryCode":165,"countryName":"Pakistan","shortName":"Pakistan","isoa2":"PK","record":"BiocapPerCap","cropLand":0.345814676839109,"grazingLand":0.0131640603032974,"forestLand":0.0278361598913929,"fishingGround":0.121198439725876,"builtupLand":0.0137879764902214,"carbon":0.0,"value":0.521801313249897,"score":"3A"},{"id":70431,"version":null,"year":1969,"countryCode":165,"countryName":"Pakistan","shortName":"Pakistan","isoa2":"PK","record":"BiocapPerCap","cropLand":0.360171887303062,"grazingLand":0.0127254859784825,"forestLand":0.0265771588264271,"fishingGround":0.117160587980539,"builtupLand":0.01545817834376,"carbon":0.0,"value":0.532093298432271,"score":"3A"},{"id":70443,"version":null,"year":1970,"countryCode":165,"countryName":"Pakistan","shortName":"Pakistan","isoa2":"PK","record":"BiocapPerCap","cropLand":0.365007987860058,"grazingLand":0.0124119998909653,"forestLand":0.039772436903011,"fishingGround":0.114274394525976,"builtupLand":0.0160086713655952,"carbon":0.0,"value":0.547475490545606,"score":"3A"},{"id":70455,"version":null,"year":1971,"countryCode":165,"countryName":"Pakistan","shortName":"Pakistan","isoa2":"PK","record":"BiocapPerCap","cropLand":0.351576442920723,"grazingLand":0.0120613136789242,"forestLand":0.0371626017372843,"fishingGround":0.111045708181982,"builtupLand":0.0160408123288191,"carbon":0.0,"value":0.527886878847733,"score":"3A"},{"id":70467,"version":null,"year":1972,"countryCode":165,"countryName":"Pakistan","shortName":"Pakistan","isoa2":"PK","record":"BiocapPerCap","cropLand":0.351276990080729,"grazingLand":0.0117769030355071,"forestLand":0.0368101415259044,"fishingGround":0.10842720557493,"builtupLand":0.0164596385312615,"carbon":0.0,"value":0.524750878748332,"score":"3A"},{"id":70479,"version":null,"year":1973,"countryCode":165,"countryName":"Pakistan","shortName":"Pakistan","isoa2":"PK","record":"BiocapPerCap","cropLand":0.349806947690176,"grazingLand":0.0113852527701165,"forestLand":0.0369611473020161,"fishingGround":0.104821372724736,"builtupLand":0.0163704078080902,"carbon":0.0,"value":0.519345128295135,"score":"3A"},{"id":70491,"version":null,"year":1974,"countryCode":165,"countryName":"Pakistan","shortName":"Pakistan","isoa2":"PK","record":"BiocapPerCap","cropLand":0.34319664975043,"grazingLand":0.0111051576977522,"forestLand":0.0352152990486208,"fishingGround":0.102242602576064,"builtupLand":0.0168771480132773,"carbon":0.0,"value":0.508636857086143,"score":"3A"},{"id":70503,"version":null,"year":1975,"countryCode":165,"countryName":"Pakistan","shortName":"Pakistan","isoa2":"PK","record":"BiocapPerCap","cropLand":0.331703035622363,"grazingLand":0.0107807657459597,"forestLand":0.0347089404924164,"fishingGround":0.099256001367086,"builtupLand":0.016634316461822,"carbon":0.0,"value":0.493083059689647,"score":"3A"},{"id":70515,"version":null,"year":1976,"countryCode":165,"countryName":"Pakistan","shortName":"Pakistan","isoa2":"PK","record":"BiocapPerCap","cropLand":0.335296609030368,"grazingLand":0.0104502163921446,"forestLand":0.0339232901059323,"fishingGround":0.096212710390612,"builtupLand":0.0175066714568426,"carbon":0.0,"value":0.493389497375899,"score":"3A"},{"id":70527,"version":null,"year":1977,"countryCode":165,"countryName":"Pakistan","shortName":"Pakistan","isoa2":"PK","record":"BiocapPerCap","cropLand":0.351149952467539,"grazingLand":0.0101827664466117,"forestLand":0.0332513570623481,"fishingGround":0.0937503609819545,"builtupLand":0.0187798716994689,"carbon":0.0,"value":0.507114308657923,"score":"3A"},{"id":70539,"version":null,"year":1978,"countryCode":165,"countryName":"Pakistan","shortName":"Pakistan","isoa2":"PK","record":"BiocapPerCap","cropLand":0.32234920840605,"grazingLand":0.00988463326283052,"forestLand":0.0308432969134335,"fishingGround":0.0910055181392232,"builtupLand":0.017500657663929,"carbon":0.0,"value":0.471583314385466,"score":"3A"},{"id":70551,"version":null,"year":1979,"countryCode":165,"countryName":"Pakistan","shortName":"Pakistan","isoa2":"PK","record":"BiocapPerCap","cropLand":0.356663622725518,"grazingLand":0.00959059459699906,"forestLand":0.0297745538768113,"fishingGround":0.0882983725703955,"builtupLand":0.0200423393759226,"carbon":0.0,"value":0.504369483145647,"score":"3A"},{"id":70563,"version":null,"year":1980,"countryCode":165,"countryName":"Pakistan","shortName":"Pakistan","isoa2":"PK","record":"BiocapPerCap","cropLand":0.341362217396727,"grazingLand":0.00928284392218998,"forestLand":0.0296147298173736,"fishingGround":0.0854649837259139,"builtupLand":0.0191576062170418,"carbon":0.0,"value":0.484882381079246,"score":"3A"},{"id":70575,"version":null,"year":1981,"countryCode":165,"countryName":"Pakistan","shortName":"Pakistan","isoa2":"PK","record":"BiocapPerCap","cropLand":0.346212436843601,"grazingLand":0.00899767738344242,"forestLand":0.0300691049203334,"fishingGround":0.0828395217664624,"builtupLand":0.0206654887148836,"carbon":0.0,"value":0.488784229628723,"score":"3A"},{"id":70587,"version":null,"year":1982,"countryCode":165,"countryName":"Pakistan","shortName":"Pakistan","isoa2":"PK","record":"BiocapPerCap","cropLand":0.344795791665781,"grazingLand":0.00865398060227042,"forestLand":0.0296928174072186,"fishingGround":0.0796751854859291,"builtupLand":0.0200085281825569,"carbon":0.0,"value":0.482826303343756,"score":"3A"},{"id":70599,"version":null,"year":1983,"countryCode":165,"countryName":"Pakistan","shortName":"Pakistan","isoa2":"PK","record":"BiocapPerCap","cropLand":0.324120818098834,"grazingLand":0.00834715835405489,"forestLand":0.0287174085672713,"fishingGround":0.0768503444490346,"builtupLand":0.0207521322176234,"carbon":0.0,"value":0.458787861686819,"score":"3A"},{"id":70611,"version":null,"year":1984,"countryCode":165,"countryName":"Pakistan","shortName":"Pakistan","isoa2":"PK","record":"BiocapPerCap","cropLand":0.324863012482161,"grazingLand":0.00802071132587271,"forestLand":0.0269377919945929,"fishingGround":0.0738448226299862,"builtupLand":0.0207842362374341,"carbon":0.0,"value":0.454450574670047,"score":"3A"},{"id":70623,"version":null,"year":1985,"countryCode":165,"countryName":"Pakistan","shortName":"Pakistan","isoa2":"PK","record":"BiocapPerCap","cropLand":0.335879435678063,"grazingLand":0.00771991317042795,"forestLand":0.0277827489645243,"fishingGround":0.0710754440133299,"builtupLand":0.0224734275234363,"carbon":0.0,"value":0.464930969349782,"score":"3A"},{"id":70635,"version":null,"year":1986,"countryCode":165,"countryName":"Pakistan","shortName":"Pakistan","isoa2":"PK","record":"BiocapPerCap","cropLand":0.363608973428461,"grazingLand":0.00742144919066671,"forestLand":0.0264810772048683,"fishingGround":0.0683275556089917,"builtupLand":0.0264037840818934,"carbon":0.0,"value":0.492242839514881,"score":"3A"},{"id":70647,"version":null,"year":1987,"countryCode":165,"countryName":"Pakistan","shortName":"Pakistan","isoa2":"PK","record":"BiocapPerCap","cropLand":0.33696059689842,"grazingLand":0.00717995068411058,"forestLand":0.0240028065072992,"fishingGround":0.0661041350596799,"builtupLand":0.0243857293386498,"carbon":0.0,"value":0.45863321848816,"score":"3A"},{"id":70659,"version":null,"year":1988,"countryCode":165,"countryName":"Pakistan","shortName":"Pakistan","isoa2":"PK","record":"BiocapPerCap","cropLand":0.314972172864654,"grazingLand":0.00694570836004529,"forestLand":0.0275691681495416,"fishingGround":0.0639475204939319,"builtupLand":0.0245428566449082,"carbon":0.0,"value":0.43797742651308,"score":"3A"},{"id":70671,"version":null,"year":1989,"countryCode":165,"countryName":"Pakistan","shortName":"Pakistan","isoa2":"PK","record":"BiocapPerCap","cropLand":0.346918004162531,"grazingLand":0.00673151701852204,"forestLand":0.0265051912523795,"fishingGround":0.0619755106582653,"builtupLand":0.0273984279955085,"carbon":0.0,"value":0.469528651087207,"score":"3A"},{"id":70683,"version":null,"year":1990,"countryCode":165,"countryName":"Pakistan","shortName":"Pakistan","isoa2":"PK","record":"BiocapPerCap","cropLand":0.342245804074733,"grazingLand":0.00655070752807096,"forestLand":0.0252648863968725,"fishingGround":0.0603108397569316,"builtupLand":0.028430557911473,"carbon":0.0,"value":0.462802795668081,"score":"3A"},{"id":70695,"version":null,"year":1991,"countryCode":165,"countryName":"Pakistan","shortName":"Pakistan","isoa2":"PK","record":"BiocapPerCap","cropLand":0.349006573854253,"grazingLand":0.00636061800659408,"forestLand":0.0241911315299032,"fishingGround":0.0585607297695544,"builtupLand":0.0297507648977036,"carbon":0.0,"value":0.467869818058008,"score":"3A"},{"id":70707,"version":null,"year":1992,"countryCode":165,"countryName":"Pakistan","shortName":"Pakistan","isoa2":"PK","record":"BiocapPerCap","cropLand":0.335625705151765,"grazingLand":0.00624862431452458,"forestLand":0.0234656499052935,"fishingGround":0.0575296299093871,"builtupLand":0.0292831758739279,"carbon":0.0,"value":0.452152785154898,"score":"3A"},{"id":70719,"version":null,"year":1993,"countryCode":165,"countryName":"Pakistan","shortName":"Pakistan","isoa2":"PK","record":"BiocapPerCap","cropLand":0.324205196904303,"grazingLand":0.00608801485011666,"forestLand":0.022472211524815,"fishingGround":0.0560509359469649,"builtupLand":0.0286840954659039,"carbon":0.0,"value":0.437500454692104,"score":"3A"},{"id":70731,"version":null,"year":1994,"countryCode":165,"countryName":"Pakistan","shortName":"Pakistan","isoa2":"PK","record":"BiocapPerCap","cropLand":0.318614065444296,"grazingLand":0.00592296330469384,"forestLand":0.0215634429204098,"fishingGround":0.0545313447783814,"builtupLand":0.0288809833761218,"carbon":0.0,"value":0.429512799823903,"score":"3A"},{"id":70743,"version":null,"year":1995,"countryCode":165,"countryName":"Pakistan","shortName":"Pakistan","isoa2":"PK","record":"BiocapPerCap","cropLand":0.346503752023815,"grazingLand":0.00575810044964863,"forestLand":0.0206600431960631,"fishingGround":0.0530134908381933,"builtupLand":0.0319664400662091,"carbon":0.0,"value":0.45790182657393,"score":"3A"},{"id":70755,"version":null,"year":1996,"countryCode":165,"countryName":"Pakistan","shortName":"Pakistan","isoa2":"PK","record":"BiocapPerCap","cropLand":0.338915642957496,"grazingLand":0.00560835112403308,"forestLand":0.0198444916878418,"fishingGround":0.0516347836463051,"builtupLand":0.031907670288631,"carbon":0.0,"value":0.447910939704307,"score":"3A"},{"id":70767,"version":null,"year":1997,"countryCode":165,"countryName":"Pakistan","shortName":"Pakistan","isoa2":"PK","record":"BiocapPerCap","cropLand":0.319582998426074,"grazingLand":0.00546956550670125,"forestLand":0.0190028236953256,"fishingGround":0.0503570167651554,"builtupLand":0.0303558952832632,"carbon":0.0,"value":0.424768299676519,"score":"3A"},{"id":70779,"version":null,"year":1998,"countryCode":165,"countryName":"Pakistan","shortName":"Pakistan","isoa2":"PK","record":"BiocapPerCap","cropLand":0.349780075851101,"grazingLand":0.00533901024023472,"forestLand":0.018211970385518,"fishingGround":0.0491550248090889,"builtupLand":0.0339415516495818,"carbon":0.0,"value":0.456427632935525,"score":"3A"},{"id":70791,"version":null,"year":1999,"countryCode":165,"countryName":"Pakistan","shortName":"Pakistan","isoa2":"PK","record":"BiocapPerCap","cropLand":0.350803858670644,"grazingLand":0.00521606497236818,"forestLand":0.0174407322523548,"fishingGround":0.0480230963391644,"builtupLand":0.0348566881759228,"carbon":0.0,"value":0.456340440410454,"score":"3A"},{"id":70803,"version":null,"year":2000,"countryCode":165,"countryName":"Pakistan","shortName":"Pakistan","isoa2":"PK","record":"BiocapPerCap","cropLand":0.357207766942519,"grazingLand":0.00510485146525329,"forestLand":0.0167183339182376,"fishingGround":0.0469991794603127,"builtupLand":0.0363766380115607,"carbon":0.0,"value":0.462406769797883,"score":"3A"},{"id":70815,"version":null,"year":2001,"countryCode":165,"countryName":"Pakistan","shortName":"Pakistan","isoa2":"PK","record":"BiocapPerCap","cropLand":0.319768021863375,"grazingLand":0.00500179672053789,"forestLand":0.0160086469624127,"fishingGround":0.0460503784081991,"builtupLand":0.0330022559907971,"carbon":0.0,"value":0.419831099945322,"score":"3A"},{"id":70827,"version":null,"year":2002,"countryCode":165,"countryName":"Pakistan","shortName":"Pakistan","isoa2":"PK","record":"BiocapPerCap","cropLand":0.303692180398215,"grazingLand":0.00489651973242248,"forestLand":0.0153689839946677,"fishingGround":0.0450811176782531,"builtupLand":0.0321072291973359,"carbon":0.0,"value":0.401146031000894,"score":"3A"},{"id":70839,"version":null,"year":2003,"countryCode":165,"countryName":"Pakistan","shortName":"Pakistan","isoa2":"PK","record":"BiocapPerCap","cropLand":0.3207224111768,"grazingLand":0.00477337969932709,"forestLand":0.0146769927196368,"fishingGround":0.0439473960501917,"builtupLand":0.0346680753853782,"carbon":0.0,"value":0.418788255031334,"score":"3A"},{"id":70851,"version":null,"year":2004,"countryCode":165,"countryName":"Pakistan","shortName":"Pakistan","isoa2":"PK","record":"BiocapPerCap","cropLand":0.332102188803231,"grazingLand":0.00466765977314261,"forestLand":0.0140515909304804,"fishingGround":0.0429740572925224,"builtupLand":0.0375867589480121,"carbon":0.0,"value":0.431382255747389,"score":"3A"},{"id":70863,"version":null,"year":2005,"countryCode":165,"countryName":"Pakistan","shortName":"Pakistan","isoa2":"PK","record":"BiocapPerCap","cropLand":0.338212582323607,"grazingLand":0.00455096600607953,"forestLand":0.013444419520475,"fishingGround":0.0418996849356717,"builtupLand":0.0391737882656877,"carbon":0.0,"value":0.437281441051521,"score":"3A"},{"id":70875,"version":null,"year":2006,"countryCode":165,"countryName":"Pakistan","shortName":"Pakistan","isoa2":"PK","record":"BiocapPerCap","cropLand":0.318096919058348,"grazingLand":0.00444981956897506,"forestLand":0.0129000632895907,"fishingGround":0.0409684532276383,"builtupLand":0.0374007803578881,"carbon":0.0,"value":0.41381603550244,"score":"3A"},{"id":70887,"version":null,"year":2007,"countryCode":165,"countryName":"Pakistan","shortName":"Pakistan","isoa2":"PK","record":"BiocapPerCap","cropLand":0.337093237762133,"grazingLand":0.00435496078435356,"forestLand":0.0123224388386987,"fishingGround":0.0400951104727788,"builtupLand":0.0406106426704982,"carbon":0.0,"value":0.434476390528462,"score":"3A"},{"id":70899,"version":null,"year":2008,"countryCode":165,"countryName":"Pakistan","shortName":"Pakistan","isoa2":"PK","record":"BiocapPerCap","cropLand":0.314172852537963,"grazingLand":0.00427864898432091,"forestLand":0.0117709373905864,"fishingGround":0.03939252548885,"builtupLand":0.039523198798777,"carbon":0.0,"value":0.409138163200497,"score":"3A"},{"id":70911,"version":null,"year":2009,"countryCode":165,"countryName":"Pakistan","shortName":"Pakistan","isoa2":"PK","record":"BiocapPerCap","cropLand":0.330210999709176,"grazingLand":0.00421050939800067,"forestLand":0.0112032772234054,"fishingGround":0.0387651801747669,"builtupLand":0.0424556220602403,"carbon":0.0,"value":0.426845588565589,"score":"3A"},{"id":70923,"version":null,"year":2010,"countryCode":165,"countryName":"Pakistan","shortName":"Pakistan","isoa2":"PK","record":"BiocapPerCap","cropLand":0.299715893397202,"grazingLand":0.0041122435894676,"forestLand":0.0107093660775533,"fishingGround":0.0378604697436223,"builtupLand":0.0393901137073082,"carbon":0.0,"value":0.391788086515154,"score":"3A"},{"id":70935,"version":null,"year":2011,"countryCode":165,"countryName":"Pakistan","shortName":"Pakistan","isoa2":"PK","record":"BiocapPerCap","cropLand":0.309612638506643,"grazingLand":0.00400555918323819,"forestLand":0.0102058119579138,"fishingGround":0.0368782512426293,"builtupLand":0.0406232479586375,"carbon":0.0,"value":0.401325508849062,"score":"3A"},{"id":70947,"version":null,"year":2012,"countryCode":165,"countryName":"Pakistan","shortName":"Pakistan","isoa2":"PK","record":"BiocapPerCap","cropLand":0.280817767272495,"grazingLand":0.00391762479239834,"forestLand":0.00969957371244181,"fishingGround":0.0360686597699007,"builtupLand":0.037479673895995,"carbon":0.0,"value":0.367983299443231,"score":"3A"},{"id":70959,"version":null,"year":2013,"countryCode":165,"countryName":"Pakistan","shortName":"Pakistan","isoa2":"PK","record":"BiocapPerCap","cropLand":0.296319893978226,"grazingLand":0.00385057817703505,"forestLand":0.00921393392699804,"fishingGround":0.0354513771850666,"builtupLand":0.0401134525094203,"carbon":0.0,"value":0.384949235776746,"score":"3A"},{"id":70971,"version":null,"year":2014,"countryCode":165,"countryName":"Pakistan","shortName":"Pakistan","isoa2":"PK","record":"BiocapPerCap","cropLand":0.297708089303891,"grazingLand":0.00378167589960641,"forestLand":0.00874546395730959,"fishingGround":0.0348170099514389,"builtupLand":0.0411884458947938,"carbon":0.0,"value":0.38624068500704,"score":"3A"},{"id":70983,"version":null,"year":2015,"countryCode":165,"countryName":"Pakistan","shortName":"Pakistan","isoa2":"PK","record":"BiocapPerCap","cropLand":0.276686810749395,"grazingLand":0.00371652420912311,"forestLand":0.00828273279501669,"fishingGround":0.0342171734989956,"builtupLand":0.0391337776642076,"carbon":0.0,"value":0.362037018916738,"score":"3A"},{"id":70995,"version":null,"year":2016,"countryCode":165,"countryName":"Pakistan","shortName":"Pakistan","isoa2":"PK","record":"BiocapPerCap","cropLand":0.279661153941686,"grazingLand":0.00364776750747936,"forestLand":0.00787383279339462,"fishingGround":0.0335841465477416,"builtupLand":0.0395394181938052,"carbon":0.0,"value":0.364306318984107,"score":"3A"},{"id":70337,"version":null,"year":1961,"countryCode":165,"countryName":"Pakistan","shortName":"Pakistan","isoa2":"PK","record":"EFConsPerCap","cropLand":0.307342008809256,"grazingLand":0.015142823126221,"forestLand":0.117621366820884,"fishingGround":0.00662362286080224,"builtupLand":0.0102046314858599,"carbon":0.0980259361855072,"value":0.554960389288531,"score":"3A"},{"id":70349,"version":null,"year":1962,"countryCode":165,"countryName":"Pakistan","shortName":"Pakistan","isoa2":"PK","record":"EFConsPerCap","cropLand":0.296287920758476,"grazingLand":0.0147021413100067,"forestLand":0.115756301810384,"fishingGround":0.00958000151670718,"builtupLand":0.0104801845684241,"carbon":0.10451610897264,"value":0.551322658936638,"score":"3A"},{"id":70361,"version":null,"year":1963,"countryCode":165,"countryName":"Pakistan","shortName":"Pakistan","isoa2":"PK","record":"EFConsPerCap","cropLand":0.304967938948379,"grazingLand":0.0141246696376857,"forestLand":0.114244918806951,"fishingGround":0.012142464623037,"builtupLand":0.0112338278166096,"carbon":0.118439816050629,"value":0.575153635883291,"score":"3A"},{"id":70373,"version":null,"year":1964,"countryCode":165,"countryName":"Pakistan","shortName":"Pakistan","isoa2":"PK","record":"EFConsPerCap","cropLand":0.294085991314621,"grazingLand":0.0143237913622166,"forestLand":0.112723621522162,"fishingGround":0.0162521905893728,"builtupLand":0.0108631361919987,"carbon":0.118015124036866,"value":0.566263855017237,"score":"3A"},{"id":70385,"version":null,"year":1965,"countryCode":165,"countryName":"Pakistan","shortName":"Pakistan","isoa2":"PK","record":"EFConsPerCap","cropLand":0.32625287642441,"grazingLand":0.0141674935222437,"forestLand":0.111695255714936,"fishingGround":0.0178523387524502,"builtupLand":0.0110020404955561,"carbon":0.125972314250211,"value":0.606942319159807,"score":"3A"},{"id":70397,"version":null,"year":1966,"countryCode":165,"countryName":"Pakistan","shortName":"Pakistan","isoa2":"PK","record":"EFConsPerCap","cropLand":0.275836388477981,"grazingLand":0.0134998614586624,"forestLand":0.112452783596194,"fishingGround":0.0259318646492308,"builtupLand":0.0105451129899241,"carbon":0.127643068817439,"value":0.565909079989431,"score":"3A"},{"id":70409,"version":null,"year":1967,"countryCode":165,"countryName":"Pakistan","shortName":"Pakistan","isoa2":"PK","record":"EFConsPerCap","cropLand":0.327208685027875,"grazingLand":0.0137313759339145,"forestLand":0.11197782259397,"fishingGround":0.025364419701298,"builtupLand":0.0121517396962331,"carbon":0.139285319317367,"value":0.629719362270658,"score":"3A"},{"id":70421,"version":null,"year":1968,"countryCode":165,"countryName":"Pakistan","shortName":"Pakistan","isoa2":"PK","record":"EFConsPerCap","cropLand":0.360710379020853,"grazingLand":0.0133380136657593,"forestLand":0.112033723045881,"fishingGround":0.0262838318116146,"builtupLand":0.0137879764902214,"carbon":0.152446744263995,"value":0.678600668298324,"score":"3A"},{"id":70433,"version":null,"year":1969,"countryCode":165,"countryName":"Pakistan","shortName":"Pakistan","isoa2":"PK","record":"EFConsPerCap","cropLand":0.339284656252887,"grazingLand":0.0130384512429317,"forestLand":0.108188476766643,"fishingGround":0.0252910013732071,"builtupLand":0.01545817834376,"carbon":0.145386123656797,"value":0.646646887636226,"score":"3A"},{"id":70445,"version":null,"year":1970,"countryCode":165,"countryName":"Pakistan","shortName":"Pakistan","isoa2":"PK","record":"EFConsPerCap","cropLand":0.361972098945595,"grazingLand":0.0138050749613143,"forestLand":0.107179605688057,"fishingGround":0.0232019239373749,"builtupLand":0.0160086713655952,"carbon":0.143619398382219,"value":0.665786773280155,"score":"3A"},{"id":70457,"version":null,"year":1971,"countryCode":165,"countryName":"Pakistan","shortName":"Pakistan","isoa2":"PK","record":"EFConsPerCap","cropLand":0.345320460429135,"grazingLand":0.0145857514094368,"forestLand":0.108631607837544,"fishingGround":0.021831348906798,"builtupLand":0.0160408123288191,"carbon":0.134357365413492,"value":0.640767346325225,"score":"3A"},{"id":70469,"version":null,"year":1972,"countryCode":165,"countryName":"Pakistan","shortName":"Pakistan","isoa2":"PK","record":"EFConsPerCap","cropLand":0.350829429355002,"grazingLand":0.0133208441242885,"forestLand":0.106175133438485,"fishingGround":0.0298505044035206,"builtupLand":0.0164596385312615,"carbon":0.136054691123264,"value":0.652690240975821,"score":"3A"},{"id":70481,"version":null,"year":1973,"countryCode":165,"countryName":"Pakistan","shortName":"Pakistan","isoa2":"PK","record":"EFConsPerCap","cropLand":0.354549866401687,"grazingLand":0.0123360325522543,"forestLand":0.105539600902325,"fishingGround":0.0290576558922306,"builtupLand":0.0163704078080902,"carbon":0.138943060168232,"value":0.656796623724819,"score":"3A"},{"id":70493,"version":null,"year":1974,"countryCode":165,"countryName":"Pakistan","shortName":"Pakistan","isoa2":"PK","record":"EFConsPerCap","cropLand":0.360119020813458,"grazingLand":0.0112833579794129,"forestLand":0.104034030823463,"fishingGround":0.0212265359681779,"builtupLand":0.0168771480132773,"carbon":0.140926841337434,"value":0.654466934935223,"score":"3A"},{"id":70505,"version":null,"year":1975,"countryCode":165,"countryName":"Pakistan","shortName":"Pakistan","isoa2":"PK","record":"EFConsPerCap","cropLand":0.345803268988225,"grazingLand":0.0112005139015813,"forestLand":0.102508544493806,"fishingGround":0.0210986404541912,"builtupLand":0.016634316461822,"carbon":0.144721149825694,"value":0.641966434125318,"score":"3A"},{"id":70517,"version":null,"year":1976,"countryCode":165,"countryName":"Pakistan","shortName":"Pakistan","isoa2":"PK","record":"EFConsPerCap","cropLand":0.345014950750239,"grazingLand":0.0110894911183984,"forestLand":0.101921106040606,"fishingGround":0.0213847405929623,"builtupLand":0.0175066714568426,"carbon":0.137025186633524,"value":0.633942146592573,"score":"3A"},{"id":70529,"version":null,"year":1977,"countryCode":165,"countryName":"Pakistan","shortName":"Pakistan","isoa2":"PK","record":"EFConsPerCap","cropLand":0.35395482249397,"grazingLand":0.0112650271559308,"forestLand":0.0991408081071708,"fishingGround":0.0271213082150394,"builtupLand":0.0187798716994689,"carbon":0.149435086187053,"value":0.659696923858633,"score":"3A"},{"id":70541,"version":null,"year":1978,"countryCode":165,"countryName":"Pakistan","shortName":"Pakistan","isoa2":"PK","record":"EFConsPerCap","cropLand":0.33127989092329,"grazingLand":0.0117209878444168,"forestLand":0.0985930737908823,"fishingGround":0.0236029548214635,"builtupLand":0.017500657663929,"carbon":0.16077757746208,"value":0.643475142506062,"score":"3A"},{"id":70553,"version":null,"year":1979,"countryCode":165,"countryName":"Pakistan","shortName":"Pakistan","isoa2":"PK","record":"EFConsPerCap","cropLand":0.387453861781636,"grazingLand":0.0112850185403092,"forestLand":0.0978482160787548,"fishingGround":0.0306270405608438,"builtupLand":0.0200423393759226,"carbon":0.171066928552763,"value":0.71832340489023,"score":"3A"},{"id":70565,"version":null,"year":1980,"countryCode":165,"countryName":"Pakistan","shortName":"Pakistan","isoa2":"PK","record":"EFConsPerCap","cropLand":0.335457350293923,"grazingLand":0.0124647256093067,"forestLand":0.0958163503924019,"fishingGround":0.0215390585175124,"builtupLand":0.0191576062170418,"carbon":0.167334567215621,"value":0.651769658245806,"score":"3A"},{"id":70577,"version":null,"year":1981,"countryCode":165,"countryName":"Pakistan","shortName":"Pakistan","isoa2":"PK","record":"EFConsPerCap","cropLand":0.335702542061088,"grazingLand":0.0134841468309934,"forestLand":0.0951705427301015,"fishingGround":0.0293105408479897,"builtupLand":0.0206654887148836,"carbon":0.169073196503425,"value":0.663406457688482,"score":"3A"},{"id":70589,"version":null,"year":1982,"countryCode":165,"countryName":"Pakistan","shortName":"Pakistan","isoa2":"PK","record":"EFConsPerCap","cropLand":0.349028643874108,"grazingLand":0.0118416858564803,"forestLand":0.095102144244332,"fishingGround":0.0314170180869424,"builtupLand":0.0200085281825569,"carbon":0.164491983280617,"value":0.671890003525036,"score":"3A"},{"id":70601,"version":null,"year":1983,"countryCode":165,"countryName":"Pakistan","shortName":"Pakistan","isoa2":"PK","record":"EFConsPerCap","cropLand":0.327663726082847,"grazingLand":0.0165082743320512,"forestLand":0.0950143124457117,"fishingGround":0.0162516282961148,"builtupLand":0.0207521322176234,"carbon":0.163967351737853,"value":0.6401574251122,"score":"3A"},{"id":70613,"version":null,"year":1984,"countryCode":165,"countryName":"Pakistan","shortName":"Pakistan","isoa2":"PK","record":"EFConsPerCap","cropLand":0.33072887213126,"grazingLand":0.0118578518139341,"forestLand":0.0958217918429171,"fishingGround":0.0158076605685604,"builtupLand":0.0207842362374341,"carbon":0.172993109454554,"value":0.64799352204866,"score":"3A"},{"id":70625,"version":null,"year":1985,"countryCode":165,"countryName":"Pakistan","shortName":"Pakistan","isoa2":"PK","record":"EFConsPerCap","cropLand":0.34586956362088,"grazingLand":0.0114095971941157,"forestLand":0.0970787122972498,"fishingGround":0.0217707310891172,"builtupLand":0.0224734275234363,"carbon":0.176688451692393,"value":0.675290483417192,"score":"3A"},{"id":70637,"version":null,"year":1986,"countryCode":165,"countryName":"Pakistan","shortName":"Pakistan","isoa2":"PK","record":"EFConsPerCap","cropLand":0.368398102895076,"grazingLand":0.0112739596135692,"forestLand":0.0950676513654227,"fishingGround":0.017872828064311,"builtupLand":0.0264037840818934,"carbon":0.179842107088016,"value":0.698858433108289,"score":"3A"},{"id":70649,"version":null,"year":1987,"countryCode":165,"countryName":"Pakistan","shortName":"Pakistan","isoa2":"PK","record":"EFConsPerCap","cropLand":0.328917387327728,"grazingLand":0.0117515108211411,"forestLand":0.0949719818156959,"fishingGround":0.0175625082112776,"builtupLand":0.0243857293386498,"carbon":0.20569065086917,"value":0.683279768383663,"score":"3A"},{"id":70661,"version":null,"year":1988,"countryCode":165,"countryName":"Pakistan","shortName":"Pakistan","isoa2":"PK","record":"EFConsPerCap","cropLand":0.321345217173205,"grazingLand":0.0134286308642307,"forestLand":0.0930401933100634,"fishingGround":0.0195800823816736,"builtupLand":0.0245428566449082,"carbon":0.212455590020858,"value":0.684392570394939,"score":"3A"},{"id":70673,"version":null,"year":1989,"countryCode":165,"countryName":"Pakistan","shortName":"Pakistan","isoa2":"PK","record":"EFConsPerCap","cropLand":0.35979489601351,"grazingLand":0.01240898549654,"forestLand":0.0955638616035919,"fishingGround":0.0205226770828907,"builtupLand":0.0273984279955085,"carbon":0.223892248606996,"value":0.739581096799037,"score":"3A"},{"id":70685,"version":null,"year":1990,"countryCode":165,"countryName":"Pakistan","shortName":"Pakistan","isoa2":"PK","record":"EFConsPerCap","cropLand":0.366951453847255,"grazingLand":0.0116607206937562,"forestLand":0.10006115757332,"fishingGround":0.0213239952523823,"builtupLand":0.028430557911473,"carbon":0.230851724911675,"value":0.759279610189861,"score":"3A"},{"id":70697,"version":null,"year":1991,"countryCode":165,"countryName":"Pakistan","shortName":"Pakistan","isoa2":"PK","record":"EFConsPerCap","cropLand":0.359224117909979,"grazingLand":0.0116141482394169,"forestLand":0.0971481795689716,"fishingGround":0.0241210627144434,"builtupLand":0.0297507648977036,"carbon":0.228648021296107,"value":0.750506294626621,"score":"3A"},{"id":70709,"version":null,"year":1992,"countryCode":165,"countryName":"Pakistan","shortName":"Pakistan","isoa2":"PK","record":"EFConsPerCap","cropLand":0.345053914100212,"grazingLand":0.0120737849129114,"forestLand":0.098053607435729,"fishingGround":0.029488431930415,"builtupLand":0.0292831758739279,"carbon":0.247636985002339,"value":0.761589899255534,"score":"3A"},{"id":70721,"version":null,"year":1993,"countryCode":165,"countryName":"Pakistan","shortName":"Pakistan","isoa2":"PK","record":"EFConsPerCap","cropLand":0.359849226215277,"grazingLand":0.0093617954020981,"forestLand":0.0934995266994563,"fishingGround":0.0313459866967273,"builtupLand":0.0286840954659039,"carbon":0.264746795849845,"value":0.787487426329308,"score":"3A"},{"id":70733,"version":null,"year":1994,"countryCode":165,"countryName":"Pakistan","shortName":"Pakistan","isoa2":"PK","record":"EFConsPerCap","cropLand":0.343892195367866,"grazingLand":0.00848693171205839,"forestLand":0.0938836419308205,"fishingGround":0.0257162164755039,"builtupLand":0.0288809833761218,"carbon":0.265097862776081,"value":0.765957831638451,"score":"3A"},{"id":70745,"version":null,"year":1995,"countryCode":165,"countryName":"Pakistan","shortName":"Pakistan","isoa2":"PK","record":"EFConsPerCap","cropLand":0.379844348907922,"grazingLand":0.00816201565126362,"forestLand":0.0886564828915875,"fishingGround":0.0268198821507418,"builtupLand":0.0319664400662091,"carbon":0.275326268062502,"value":0.810775437730226,"score":"3A"},{"id":70757,"version":null,"year":1996,"countryCode":165,"countryName":"Pakistan","shortName":"Pakistan","isoa2":"PK","record":"EFConsPerCap","cropLand":0.356676447909252,"grazingLand":0.0079806496514234,"forestLand":0.10602619471281,"fishingGround":0.0260687300762323,"builtupLand":0.031907670288631,"carbon":0.284685163970315,"value":0.813344856608663,"score":"3A"},{"id":70769,"version":null,"year":1997,"countryCode":165,"countryName":"Pakistan","shortName":"Pakistan","isoa2":"PK","record":"EFConsPerCap","cropLand":0.344190468891272,"grazingLand":0.00711420191224637,"forestLand":0.109843543369241,"fishingGround":0.0263792932763444,"builtupLand":0.0303558952832632,"carbon":0.288044083117975,"value":0.805927485850343,"score":"3A"},{"id":70781,"version":null,"year":1998,"countryCode":165,"countryName":"Pakistan","shortName":"Pakistan","isoa2":"PK","record":"EFConsPerCap","cropLand":0.376359368232877,"grazingLand":0.00705165266005876,"forestLand":0.109535960601321,"fishingGround":0.0275653126463528,"builtupLand":0.0339415516495818,"carbon":0.280912551821758,"value":0.835366397611949,"score":"3A"},{"id":70793,"version":null,"year":1999,"countryCode":165,"countryName":"Pakistan","shortName":"Pakistan","isoa2":"PK","record":"EFConsPerCap","cropLand":0.389807261673586,"grazingLand":0.00690673655033447,"forestLand":0.10914275790425,"fishingGround":0.03265108986003,"builtupLand":0.0348566881759228,"carbon":0.294342706776879,"value":0.867707240941002,"score":"3A"},{"id":70805,"version":null,"year":2000,"countryCode":165,"countryName":"Pakistan","shortName":"Pakistan","isoa2":"PK","record":"EFConsPerCap","cropLand":0.376642119532011,"grazingLand":0.00851191454169125,"forestLand":0.108366338781342,"fishingGround":0.0287008540158852,"builtupLand":0.0363766380115607,"carbon":0.283482453735076,"value":0.842080318617566,"score":"3A"},{"id":70817,"version":null,"year":2001,"countryCode":165,"countryName":"Pakistan","shortName":"Pakistan","isoa2":"PK","record":"EFConsPerCap","cropLand":0.323477263569745,"grazingLand":0.00864240768825178,"forestLand":0.112561643303616,"fishingGround":0.0250322386783312,"builtupLand":0.0330022559907971,"carbon":0.285593985292845,"value":0.788309794523587,"score":"3A"},{"id":70829,"version":null,"year":2002,"countryCode":165,"countryName":"Pakistan","shortName":"Pakistan","isoa2":"PK","record":"EFConsPerCap","cropLand":0.313844267828503,"grazingLand":0.00895243311328105,"forestLand":0.109917389541741,"fishingGround":0.0240997934041034,"builtupLand":0.0321072291973359,"carbon":0.314368018334378,"value":0.803289131419343,"score":"3A"},{"id":70841,"version":null,"year":2003,"countryCode":165,"countryName":"Pakistan","shortName":"Pakistan","isoa2":"PK","record":"EFConsPerCap","cropLand":0.323608752695198,"grazingLand":0.00850355313974506,"forestLand":0.10758284763142,"fishingGround":0.02197285120434,"builtupLand":0.0346680753853782,"carbon":0.308852911485716,"value":0.805188991541797,"score":"3A"},{"id":70853,"version":null,"year":2004,"countryCode":165,"countryName":"Pakistan","shortName":"Pakistan","isoa2":"PK","record":"EFConsPerCap","cropLand":0.346610367264925,"grazingLand":0.0105126050107515,"forestLand":0.0945326920981201,"fishingGround":0.0189061824116583,"builtupLand":0.0375867589480121,"carbon":0.33394240821285,"value":0.842091013946317,"score":"3A"},{"id":70865,"version":null,"year":2005,"countryCode":165,"countryName":"Pakistan","shortName":"Pakistan","isoa2":"PK","record":"EFConsPerCap","cropLand":0.355811410165216,"grazingLand":0.0115427735366136,"forestLand":0.0943443266684486,"fishingGround":0.0167639102807339,"builtupLand":0.0391737882656877,"carbon":0.359614087089084,"value":0.877250296005784,"score":"3A"},{"id":70877,"version":null,"year":2006,"countryCode":165,"countryName":"Pakistan","shortName":"Pakistan","isoa2":"PK","record":"EFConsPerCap","cropLand":0.336054236057631,"grazingLand":0.0112830838682496,"forestLand":0.094551618243895,"fishingGround":0.0159606004866366,"builtupLand":0.0374007803578881,"carbon":0.375090312872046,"value":0.870340631886346,"score":"3A"},{"id":70889,"version":null,"year":2007,"countryCode":165,"countryName":"Pakistan","shortName":"Pakistan","isoa2":"PK","record":"EFConsPerCap","cropLand":0.357759729078729,"grazingLand":0.0112607388690653,"forestLand":0.101460670591172,"fishingGround":0.0152494707219195,"builtupLand":0.0406106426704982,"carbon":0.399787760849034,"value":0.926129012780418,"score":"3A"},{"id":70901,"version":null,"year":2008,"countryCode":165,"countryName":"Pakistan","shortName":"Pakistan","isoa2":"PK","record":"EFConsPerCap","cropLand":0.350701970222024,"grazingLand":0.00790302087723066,"forestLand":0.100891867685529,"fishingGround":0.0152648618766408,"builtupLand":0.039523198798777,"carbon":0.385581018650319,"value":0.899865938110521,"score":"3A"},{"id":70913,"version":null,"year":2009,"countryCode":165,"countryName":"Pakistan","shortName":"Pakistan","isoa2":"PK","record":"EFConsPerCap","cropLand":0.36568308980767,"grazingLand":0.00686220285353979,"forestLand":0.0982869096295154,"fishingGround":0.0151379412474329,"builtupLand":0.0424556220602403,"carbon":0.384965349118558,"value":0.913391114716956,"score":"3A"},{"id":70925,"version":null,"year":2010,"countryCode":165,"countryName":"Pakistan","shortName":"Pakistan","isoa2":"PK","record":"EFConsPerCap","cropLand":0.311482807560201,"grazingLand":0.00578590040356503,"forestLand":0.0941247682225757,"fishingGround":0.0166829827031902,"builtupLand":0.0393901137073082,"carbon":0.382538036569913,"value":0.850004609166753,"score":"3A"},{"id":70937,"version":null,"year":2011,"countryCode":165,"countryName":"Pakistan","shortName":"Pakistan","isoa2":"PK","record":"EFConsPerCap","cropLand":0.305459015866063,"grazingLand":0.00640979976197089,"forestLand":0.0923705278694852,"fishingGround":0.0151122059698277,"builtupLand":0.0406232479586375,"carbon":0.365166728814831,"value":0.825141526240815,"score":"3A"},{"id":70949,"version":null,"year":2012,"countryCode":165,"countryName":"Pakistan","shortName":"Pakistan","isoa2":"PK","record":"EFConsPerCap","cropLand":0.286777834380379,"grazingLand":0.00527922088947589,"forestLand":0.0889932901501965,"fishingGround":0.0151913047813675,"builtupLand":0.037479673895995,"carbon":0.353795812438338,"value":0.787517136535751,"score":"3A"},{"id":70961,"version":null,"year":2013,"countryCode":165,"countryName":"Pakistan","shortName":"Pakistan","isoa2":"PK","record":"EFConsPerCap","cropLand":0.30144166578175,"grazingLand":0.00508791134836301,"forestLand":0.0871192947150981,"fishingGround":0.0151400080540875,"builtupLand":0.0401134525094203,"carbon":0.348363858719816,"value":0.797266191128534,"score":"3A"},{"id":70973,"version":null,"year":2014,"countryCode":165,"countryName":"Pakistan","shortName":"Pakistan","isoa2":"PK","record":"EFConsPerCap","cropLand":0.320792193204106,"grazingLand":0.00192967508204079,"forestLand":0.0865082268839925,"fishingGround":0.0140107989507106,"builtupLand":0.0411884458947938,"carbon":0.362871515886611,"value":0.827300855902255,"score":"3A"},{"id":70985,"version":null,"year":2015,"countryCode":165,"countryName":"Pakistan","shortName":"Pakistan","isoa2":"PK","record":"EFConsPerCap","cropLand":0.298923788427789,"grazingLand":0.00314970078742008,"forestLand":0.0834725983875184,"fishingGround":0.0149801428626559,"builtupLand":0.0391337776642076,"carbon":0.370570491965025,"value":0.810230500094616,"score":"3A"},{"id":70997,"version":null,"year":2016,"countryCode":165,"countryName":"Pakistan","shortName":"Pakistan","isoa2":"PK","record":"EFConsPerCap","cropLand":0.310301706851471,"grazingLand":0.00343565496673008,"forestLand":0.0841239672230366,"fishingGround":0.0204089830055704,"builtupLand":0.0395394181938052,"carbon":0.376112912583508,"value":0.833922642824121,"score":"3A"}]