[{"id":33867,"version":null,"year":1961,"countryCode":75,"countryName":"Gambia","shortName":"Gambia","isoa2":"GM","record":"BiocapPerCap","cropLand":0.803304133643404,"grazingLand":0.491602684028499,"forestLand":0.920172420261633,"fishingGround":1.60917341079145,"builtupLand":0.0693439314509196,"carbon":0.0,"value":3.89359658017591,"score":"3A"},{"id":33879,"version":null,"year":1962,"countryCode":75,"countryName":"Gambia","shortName":"Gambia","isoa2":"GM","record":"BiocapPerCap","cropLand":0.801117036409574,"grazingLand":0.481773022932278,"forestLand":0.904300922646082,"fishingGround":1.57699777427232,"builtupLand":0.0698375390068061,"carbon":0.0,"value":3.83402629526706,"score":"3A"},{"id":33891,"version":null,"year":1963,"countryCode":75,"countryName":"Gambia","shortName":"Gambia","isoa2":"GM","record":"BiocapPerCap","cropLand":0.756977448686653,"grazingLand":0.473294932364192,"forestLand":0.890612298359892,"fishingGround":1.54924626200504,"builtupLand":0.066413354952879,"carbon":0.0,"value":3.73654429636866,"score":"3A"},{"id":33903,"version":null,"year":1964,"countryCode":75,"countryName":"Gambia","shortName":"Gambia","isoa2":"GM","record":"BiocapPerCap","cropLand":0.767843259287652,"grazingLand":0.465716071677204,"forestLand":0.878143421083222,"fishingGround":1.52443821783072,"builtupLand":0.0677775876512601,"carbon":0.0,"value":3.70391855753006,"score":"3A"},{"id":33915,"version":null,"year":1965,"countryCode":75,"countryName":"Gambia","shortName":"Gambia","isoa2":"GM","record":"BiocapPerCap","cropLand":0.907570145416761,"grazingLand":0.4567504604303,"forestLand":0.865270170429921,"fishingGround":1.4950908938662,"builtupLand":0.0807560145824916,"carbon":0.0,"value":3.80543768472567,"score":"3A"},{"id":33927,"version":null,"year":1966,"countryCode":75,"countryName":"Gambia","shortName":"Gambia","isoa2":"GM","record":"BiocapPerCap","cropLand":0.961436672963348,"grazingLand":0.448408082301614,"forestLand":0.851257108534188,"fishingGround":1.46778361198271,"builtupLand":0.0864361369611538,"carbon":0.0,"value":3.81532161274301,"score":"3A"},{"id":33939,"version":null,"year":1967,"countryCode":75,"countryName":"Gambia","shortName":"Gambia","isoa2":"GM","record":"BiocapPerCap","cropLand":0.840843155718014,"grazingLand":0.438339406581441,"forestLand":0.834617112352607,"fishingGround":1.43482560386523,"builtupLand":0.0759281364912207,"carbon":0.0,"value":3.62455341500852,"score":"3A"},{"id":33951,"version":null,"year":1968,"countryCode":75,"countryName":"Gambia","shortName":"Gambia","isoa2":"GM","record":"BiocapPerCap","cropLand":0.931841540516106,"grazingLand":0.428043739044582,"forestLand":0.814496905176313,"fishingGround":1.40112457865744,"builtupLand":0.0859990156971475,"carbon":0.0,"value":3.66150577909159,"score":"3A"},{"id":33963,"version":null,"year":1969,"countryCode":75,"countryName":"Gambia","shortName":"Gambia","isoa2":"GM","record":"BiocapPerCap","cropLand":0.835377234301455,"grazingLand":0.415024833105647,"forestLand":0.793973279289303,"fishingGround":1.358509519881,"builtupLand":0.0777729939245687,"carbon":0.0,"value":3.48065786050197,"score":"3A"},{"id":33975,"version":null,"year":1970,"countryCode":75,"countryName":"Gambia","shortName":"Gambia","isoa2":"GM","record":"BiocapPerCap","cropLand":0.824819746304136,"grazingLand":0.405205662669672,"forestLand":0.772895513746849,"fishingGround":1.32636822266082,"builtupLand":0.0782261512267121,"carbon":0.0,"value":3.40751529660818,"score":"3A"},{"id":33987,"version":null,"year":1971,"countryCode":75,"countryName":"Gambia","shortName":"Gambia","isoa2":"GM","record":"BiocapPerCap","cropLand":0.863138677386371,"grazingLand":0.393228391712209,"forestLand":0.751171113178846,"fishingGround":1.28716276958913,"builtupLand":0.082378082740514,"carbon":0.0,"value":3.37707903460707,"score":"3A"},{"id":33999,"version":null,"year":1972,"countryCode":75,"countryName":"Gambia","shortName":"Gambia","isoa2":"GM","record":"BiocapPerCap","cropLand":0.802930096142941,"grazingLand":0.382649936180633,"forestLand":0.728657373408125,"fishingGround":1.25253608848731,"builtupLand":0.0762382107392432,"carbon":0.0,"value":3.24301170495826,"score":"3A"},{"id":34011,"version":null,"year":1973,"countryCode":75,"countryName":"Gambia","shortName":"Gambia","isoa2":"GM","record":"BiocapPerCap","cropLand":0.897748654848369,"grazingLand":0.368409702314254,"forestLand":0.706941489515542,"fishingGround":1.20592323130466,"builtupLand":0.0850009170816108,"carbon":0.0,"value":3.26402399506444,"score":"3A"},{"id":34023,"version":null,"year":1974,"countryCode":75,"countryName":"Gambia","shortName":"Gambia","isoa2":"GM","record":"BiocapPerCap","cropLand":0.726641625610332,"grazingLand":0.358222815083026,"forestLand":0.684153067364898,"fishingGround":1.17257827896044,"builtupLand":0.0599813425727529,"carbon":0.0,"value":3.00157712959145,"score":"3A"},{"id":34035,"version":null,"year":1975,"countryCode":75,"countryName":"Gambia","shortName":"Gambia","isoa2":"GM","record":"BiocapPerCap","cropLand":0.666731661697709,"grazingLand":0.347345781424688,"forestLand":0.664028703418949,"fishingGround":1.13697425579309,"builtupLand":0.0587557288982437,"carbon":0.0,"value":2.87383613123268,"score":"3A"},{"id":34047,"version":null,"year":1976,"countryCode":75,"countryName":"Gambia","shortName":"Gambia","isoa2":"GM","record":"BiocapPerCap","cropLand":0.69063510640754,"grazingLand":0.336985893518506,"forestLand":0.645014960510846,"fishingGround":1.10306301669896,"builtupLand":0.0630289309182337,"carbon":0.0,"value":2.83872790805408,"score":"3A"},{"id":34059,"version":null,"year":1977,"countryCode":75,"countryName":"Gambia","shortName":"Gambia","isoa2":"GM","record":"BiocapPerCap","cropLand":0.485302940379558,"grazingLand":0.329086880684522,"forestLand":0.627058031422287,"fishingGround":1.07720701176467,"builtupLand":0.0437291427132166,"carbon":0.0,"value":2.56238400696426,"score":"3A"},{"id":34071,"version":null,"year":1978,"countryCode":75,"countryName":"Gambia","shortName":"Gambia","isoa2":"GM","record":"BiocapPerCap","cropLand":0.643257046665713,"grazingLand":0.320282342942526,"forestLand":0.608421956270505,"fishingGround":1.04838693309336,"builtupLand":0.0573373040842095,"carbon":0.0,"value":2.67768558305631,"score":"3A"},{"id":34083,"version":null,"year":1979,"countryCode":75,"countryName":"Gambia","shortName":"Gambia","isoa2":"GM","record":"BiocapPerCap","cropLand":0.35850428533375,"grazingLand":0.311329361493322,"forestLand":0.590557439909474,"fishingGround":1.01908095051143,"builtupLand":0.0350615087871083,"carbon":0.0,"value":2.31453354603509,"score":"3A"},{"id":34095,"version":null,"year":1980,"countryCode":75,"countryName":"Gambia","shortName":"Gambia","isoa2":"GM","record":"BiocapPerCap","cropLand":0.361315160924273,"grazingLand":0.301413840655542,"forestLand":0.568979309412121,"fishingGround":0.986624267493448,"builtupLand":0.0380637753179785,"carbon":0.0,"value":2.25639635380336,"score":"3A"},{"id":34107,"version":null,"year":1981,"countryCode":75,"countryName":"Gambia","shortName":"Gambia","isoa2":"GM","record":"BiocapPerCap","cropLand":0.507483824655651,"grazingLand":0.291831692908071,"forestLand":0.550050756115601,"fishingGround":0.955258821627388,"builtupLand":0.0487447812283079,"carbon":0.0,"value":2.35336987653502,"score":"3A"},{"id":34119,"version":null,"year":1982,"countryCode":75,"countryName":"Gambia","shortName":"Gambia","isoa2":"GM","record":"BiocapPerCap","cropLand":0.686468800353755,"grazingLand":0.280037304140245,"forestLand":0.531254908445767,"fishingGround":0.916652000675566,"builtupLand":0.0613736443244551,"carbon":0.0,"value":2.47578665793979,"score":"3A"},{"id":34131,"version":null,"year":1983,"countryCode":75,"countryName":"Gambia","shortName":"Gambia","isoa2":"GM","record":"BiocapPerCap","cropLand":0.479947974627853,"grazingLand":0.268954917818826,"forestLand":0.511608394075736,"fishingGround":0.880375792314767,"builtupLand":0.0490945712585319,"carbon":0.0,"value":2.18998165009571,"score":"3A"},{"id":34143,"version":null,"year":1984,"countryCode":75,"countryName":"Gambia","shortName":"Gambia","isoa2":"GM","record":"BiocapPerCap","cropLand":0.46136544128799,"grazingLand":0.256594112435179,"forestLand":0.490970617284087,"fishingGround":0.839914907934853,"builtupLand":0.0531242313529146,"carbon":0.0,"value":2.10196931029502,"score":"3A"},{"id":34155,"version":null,"year":1985,"countryCode":75,"countryName":"Gambia","shortName":"Gambia","isoa2":"GM","record":"BiocapPerCap","cropLand":0.391594840765231,"grazingLand":0.244443141857305,"forestLand":0.469466913801403,"fishingGround":0.800140880240385,"builtupLand":0.0470837346269653,"carbon":0.0,"value":1.95272951129129,"score":"3A"},{"id":34167,"version":null,"year":1986,"countryCode":75,"countryName":"Gambia","shortName":"Gambia","isoa2":"GM","record":"BiocapPerCap","cropLand":0.451405899045937,"grazingLand":0.231829100946152,"forestLand":0.447107240147009,"fishingGround":0.758851074679262,"builtupLand":0.0540221226193639,"carbon":0.0,"value":1.94321543743772,"score":"3A"},{"id":34179,"version":null,"year":1987,"countryCode":75,"countryName":"Gambia","shortName":"Gambia","isoa2":"GM","record":"BiocapPerCap","cropLand":0.447931084089818,"grazingLand":0.22075781941428,"forestLand":0.426211558919776,"fishingGround":0.722611215859772,"builtupLand":0.054148470627697,"carbon":0.0,"value":1.87166014891134,"score":"3A"},{"id":34191,"version":null,"year":1988,"countryCode":75,"countryName":"Gambia","shortName":"Gambia","isoa2":"GM","record":"BiocapPerCap","cropLand":0.350612719341627,"grazingLand":0.210151742177498,"forestLand":0.406551371790564,"fishingGround":0.68789412004904,"builtupLand":0.0411682932211934,"carbon":0.0,"value":1.69637824657992,"score":"3A"},{"id":34203,"version":null,"year":1989,"countryCode":75,"countryName":"Gambia","shortName":"Gambia","isoa2":"GM","record":"BiocapPerCap","cropLand":0.440046818917884,"grazingLand":0.200845262530092,"forestLand":0.388809513638629,"fishingGround":0.657431024376013,"builtupLand":0.0592300642312387,"carbon":0.0,"value":1.74636268369386,"score":"3A"},{"id":34215,"version":null,"year":1990,"countryCode":75,"countryName":"Gambia","shortName":"Gambia","isoa2":"GM","record":"BiocapPerCap","cropLand":0.295759425915979,"grazingLand":0.190496843851721,"forestLand":0.364704805898519,"fishingGround":0.633053124615867,"builtupLand":0.0401262355338766,"carbon":0.0,"value":1.52414043581596,"score":"3A"},{"id":34227,"version":null,"year":1991,"countryCode":75,"countryName":"Gambia","shortName":"Gambia","isoa2":"GM","record":"BiocapPerCap","cropLand":0.321423326106189,"grazingLand":0.182263765719464,"forestLand":0.35398568241364,"fishingGround":0.610340480656291,"builtupLand":0.0431404475311011,"carbon":0.0,"value":1.51115370242668,"score":"3A"},{"id":34239,"version":null,"year":1992,"countryCode":75,"countryName":"Gambia","shortName":"Gambia","isoa2":"GM","record":"BiocapPerCap","cropLand":0.238424030491397,"grazingLand":0.178258707742167,"forestLand":0.349078139159864,"fishingGround":0.596928879061915,"builtupLand":0.0397417153451006,"carbon":0.0,"value":1.40243147180044,"score":"3A"},{"id":34251,"version":null,"year":1993,"countryCode":75,"countryName":"Gambia","shortName":"Gambia","isoa2":"GM","record":"BiocapPerCap","cropLand":0.266779464381745,"grazingLand":0.173198637926469,"forestLand":0.340524538304471,"fishingGround":0.579984395163669,"builtupLand":0.0460438854284374,"carbon":0.0,"value":1.40653092120479,"score":"3A"},{"id":34263,"version":null,"year":1994,"countryCode":75,"countryName":"Gambia","shortName":"Gambia","isoa2":"GM","record":"BiocapPerCap","cropLand":0.262779078483527,"grazingLand":0.159945940126811,"forestLand":0.333080495069772,"fishingGround":0.56296173298762,"builtupLand":0.0418445153568291,"carbon":0.0,"value":1.36061176202456,"score":"3A"},{"id":34275,"version":null,"year":1995,"countryCode":75,"countryName":"Gambia","shortName":"Gambia","isoa2":"GM","record":"BiocapPerCap","cropLand":0.243600806496259,"grazingLand":0.152985450693631,"forestLand":0.325258666377666,"fishingGround":0.545798904787032,"builtupLand":0.0388406101661489,"carbon":0.0,"value":1.30648443852074,"score":"3A"},{"id":34287,"version":null,"year":1996,"countryCode":75,"countryName":"Gambia","shortName":"Gambia","isoa2":"GM","record":"BiocapPerCap","cropLand":0.189829099344459,"grazingLand":0.146507378101632,"forestLand":0.318368395243984,"fishingGround":0.529906832932387,"builtupLand":0.0303341063659747,"carbon":0.0,"value":1.21494581198844,"score":"3A"},{"id":34299,"version":null,"year":1997,"countryCode":75,"countryName":"Gambia","shortName":"Gambia","isoa2":"GM","record":"BiocapPerCap","cropLand":0.245997017701235,"grazingLand":0.136471188181191,"forestLand":0.310646121075821,"fishingGround":0.514944106211207,"builtupLand":0.0375488657672461,"carbon":0.0,"value":1.2456072989367,"score":"3A"},{"id":34311,"version":null,"year":1998,"countryCode":75,"countryName":"Gambia","shortName":"Gambia","isoa2":"GM","record":"BiocapPerCap","cropLand":0.227399704738895,"grazingLand":0.132628462064217,"forestLand":0.303211880991809,"fishingGround":0.500444421756989,"builtupLand":0.0365897221317141,"carbon":0.0,"value":1.20027419168363,"score":"3A"},{"id":34323,"version":null,"year":1999,"countryCode":75,"countryName":"Gambia","shortName":"Gambia","isoa2":"GM","record":"BiocapPerCap","cropLand":0.34225332088336,"grazingLand":0.113985463387658,"forestLand":0.29544291933676,"fishingGround":0.486138131580088,"builtupLand":0.0474476246589389,"carbon":0.0,"value":1.28526745984681,"score":"3A"},{"id":34335,"version":null,"year":2000,"countryCode":75,"countryName":"Gambia","shortName":"Gambia","isoa2":"GM","record":"BiocapPerCap","cropLand":0.362385234220473,"grazingLand":0.0963191620134396,"forestLand":0.287806327191704,"fishingGround":0.472334891287441,"builtupLand":0.0445034498165493,"carbon":0.0,"value":1.26334906452961,"score":"3A"},{"id":34347,"version":null,"year":2001,"countryCode":75,"countryName":"Gambia","shortName":"Gambia","isoa2":"GM","record":"BiocapPerCap","cropLand":0.377947531717024,"grazingLand":0.0823265086958953,"forestLand":0.279990936112404,"fishingGround":0.458691222761254,"builtupLand":0.0447318893491198,"carbon":0.0,"value":1.2436880886357,"score":"3A"},{"id":34359,"version":null,"year":2002,"countryCode":75,"countryName":"Gambia","shortName":"Gambia","isoa2":"GM","record":"BiocapPerCap","cropLand":0.228339336457444,"grazingLand":0.078747731996045,"forestLand":0.272824157718242,"fishingGround":0.444425186706477,"builtupLand":0.0298514822177437,"carbon":0.0,"value":1.05418789509595,"score":"3A"},{"id":34371,"version":null,"year":2003,"countryCode":75,"countryName":"Gambia","shortName":"Gambia","isoa2":"GM","record":"BiocapPerCap","cropLand":0.283959865689502,"grazingLand":0.0660903131702719,"forestLand":0.264295145264597,"fishingGround":0.428385768094799,"builtupLand":0.0358220484506558,"carbon":0.0,"value":1.07855314066983,"score":"3A"},{"id":34383,"version":null,"year":2004,"countryCode":75,"countryName":"Gambia","shortName":"Gambia","isoa2":"GM","record":"BiocapPerCap","cropLand":0.34527102756877,"grazingLand":0.0632469317375498,"forestLand":0.256706830306921,"fishingGround":0.414055025217508,"builtupLand":0.0435558871760204,"carbon":0.0,"value":1.12283570200677,"score":"3A"},{"id":34395,"version":null,"year":2005,"countryCode":75,"countryName":"Gambia","shortName":"Gambia","isoa2":"GM","record":"BiocapPerCap","cropLand":0.280695119378301,"grazingLand":0.0600426782047094,"forestLand":0.249313872375218,"fishingGround":0.399063882416683,"builtupLand":0.0349029062101319,"carbon":0.0,"value":1.02401845858504,"score":"3A"},{"id":34407,"version":null,"year":2006,"countryCode":75,"countryName":"Gambia","shortName":"Gambia","isoa2":"GM","record":"BiocapPerCap","cropLand":0.289251180087697,"grazingLand":0.0580410789321954,"forestLand":0.242896090259398,"fishingGround":0.385760578823054,"builtupLand":0.0411201605559416,"carbon":0.0,"value":1.01706908865829,"score":"3A"},{"id":34419,"version":null,"year":2007,"countryCode":75,"countryName":"Gambia","shortName":"Gambia","isoa2":"GM","record":"BiocapPerCap","cropLand":0.190996784207601,"grazingLand":0.0533122509256978,"forestLand":0.235729253689017,"fishingGround":0.373279385763509,"builtupLand":0.0271180707416643,"carbon":0.0,"value":0.880435745327489,"score":"3A"},{"id":34431,"version":null,"year":2008,"countryCode":75,"countryName":"Gambia","shortName":"Gambia","isoa2":"GM","record":"BiocapPerCap","cropLand":0.27569747103745,"grazingLand":0.0484720995997246,"forestLand":0.228941723094877,"fishingGround":0.362662271209663,"builtupLand":0.0330073502957658,"carbon":0.0,"value":0.948780915237481,"score":"3A"},{"id":34443,"version":null,"year":2009,"countryCode":75,"countryName":"Gambia","shortName":"Gambia","isoa2":"GM","record":"BiocapPerCap","cropLand":0.319996353796975,"grazingLand":0.0458303779055939,"forestLand":0.221708418053955,"fishingGround":0.352982448096741,"builtupLand":0.0344268047633722,"carbon":0.0,"value":0.974944402616636,"score":"3A"},{"id":34455,"version":null,"year":2010,"countryCode":75,"countryName":"Gambia","shortName":"Gambia","isoa2":"GM","record":"BiocapPerCap","cropLand":0.34250554543751,"grazingLand":0.0416761760145645,"forestLand":0.21581554516972,"fishingGround":0.341048759928118,"builtupLand":0.036191543888186,"carbon":0.0,"value":0.977237570438099,"score":"3A"},{"id":34467,"version":null,"year":2011,"countryCode":75,"countryName":"Gambia","shortName":"Gambia","isoa2":"GM","record":"BiocapPerCap","cropLand":0.194436742035452,"grazingLand":0.0401706028414392,"forestLand":0.209537229244384,"fishingGround":0.328728199051901,"builtupLand":0.0212038182802935,"carbon":0.0,"value":0.794076591453469,"score":"3A"},{"id":34479,"version":null,"year":2012,"countryCode":75,"countryName":"Gambia","shortName":"Gambia","isoa2":"GM","record":"BiocapPerCap","cropLand":0.239010689508143,"grazingLand":0.0388879531106953,"forestLand":0.203078646315287,"fishingGround":0.318231888163409,"builtupLand":0.027501376283798,"carbon":0.0,"value":0.826710553381333,"score":"3A"},{"id":34491,"version":null,"year":2013,"countryCode":75,"countryName":"Gambia","shortName":"Gambia","isoa2":"GM","record":"BiocapPerCap","cropLand":0.200477352980702,"grazingLand":0.0378380305737281,"forestLand":0.196891334855207,"fishingGround":0.309640054327021,"builtupLand":0.0237997701700746,"carbon":0.0,"value":0.768646542906733,"score":"3A"},{"id":34503,"version":null,"year":2014,"countryCode":75,"countryName":"Gambia","shortName":"Gambia","isoa2":"GM","record":"BiocapPerCap","cropLand":0.163143554246936,"grazingLand":0.0367867972950347,"forestLand":0.190877718075171,"fishingGround":0.301037494294443,"builtupLand":0.0199773126774348,"carbon":0.0,"value":0.711822876589019,"score":"3A"},{"id":34515,"version":null,"year":2015,"countryCode":75,"countryName":"Gambia","shortName":"Gambia","isoa2":"GM","record":"BiocapPerCap","cropLand":0.192094055477694,"grazingLand":0.0357855610258132,"forestLand":0.184773761702147,"fishingGround":0.292844074919937,"builtupLand":0.0242550467033379,"carbon":0.0,"value":0.729752499828929,"score":"3A"},{"id":34527,"version":null,"year":2016,"countryCode":75,"countryName":"Gambia","shortName":"Gambia","isoa2":"GM","record":"BiocapPerCap","cropLand":0.208286993541583,"grazingLand":0.0347617001414376,"forestLand":0.179660663847507,"fishingGround":0.284465511473204,"builtupLand":0.0271097458012577,"carbon":0.0,"value":0.73428461480499,"score":"3A"},{"id":33869,"version":null,"year":1961,"countryCode":75,"countryName":"Gambia","shortName":"Gambia","isoa2":"GM","record":"EFConsPerCap","cropLand":0.456951482713159,"grazingLand":0.27258854807999,"forestLand":0.230527444406688,"fishingGround":0.0386543982070861,"builtupLand":0.0693439314509196,"carbon":0.0593578270798918,"value":1.12742363193773,"score":"3A"},{"id":33881,"version":null,"year":1962,"countryCode":75,"countryName":"Gambia","shortName":"Gambia","isoa2":"GM","record":"EFConsPerCap","cropLand":0.463398792508885,"grazingLand":0.294352071612185,"forestLand":0.230294128208483,"fishingGround":0.0410485279146624,"builtupLand":0.0698375390068061,"carbon":0.0623294574076266,"value":1.16126051665865,"score":"3A"},{"id":33893,"version":null,"year":1963,"countryCode":75,"countryName":"Gambia","shortName":"Gambia","isoa2":"GM","record":"EFConsPerCap","cropLand":0.478926068768488,"grazingLand":0.341396117281012,"forestLand":0.23312196776699,"fishingGround":0.0406014237831543,"builtupLand":0.066413354952879,"carbon":0.0663171334955863,"value":1.22677606604811,"score":"3A"},{"id":33905,"version":null,"year":1964,"countryCode":75,"countryName":"Gambia","shortName":"Gambia","isoa2":"GM","record":"EFConsPerCap","cropLand":0.505513735837342,"grazingLand":0.353245306205813,"forestLand":0.234295771783249,"fishingGround":0.0355988515407228,"builtupLand":0.0677775876512601,"carbon":0.0403882368948853,"value":1.23681948991327,"score":"3A"},{"id":33917,"version":null,"year":1965,"countryCode":75,"countryName":"Gambia","shortName":"Gambia","isoa2":"GM","record":"EFConsPerCap","cropLand":0.474059688605917,"grazingLand":0.364357419690467,"forestLand":0.247060675554572,"fishingGround":0.0439029570929452,"builtupLand":0.0807560145824916,"carbon":0.0522837850522701,"value":1.26242054057866,"score":"3A"},{"id":33929,"version":null,"year":1966,"countryCode":75,"countryName":"Gambia","shortName":"Gambia","isoa2":"GM","record":"EFConsPerCap","cropLand":0.533426778993239,"grazingLand":0.378406667784719,"forestLand":0.247467707715803,"fishingGround":0.0426159311227561,"builtupLand":0.0864361369611538,"carbon":0.0598991177785807,"value":1.34825234035625,"score":"3A"},{"id":33941,"version":null,"year":1967,"countryCode":75,"countryName":"Gambia","shortName":"Gambia","isoa2":"GM","record":"EFConsPerCap","cropLand":0.324032590489178,"grazingLand":0.399292508549287,"forestLand":0.247926951527406,"fishingGround":0.0417540670343179,"builtupLand":0.0759281364912207,"carbon":0.0531440925372784,"value":1.14207834662869,"score":"3A"},{"id":33953,"version":null,"year":1968,"countryCode":75,"countryName":"Gambia","shortName":"Gambia","isoa2":"GM","record":"EFConsPerCap","cropLand":0.398364920259412,"grazingLand":0.422641117268938,"forestLand":0.248429240766293,"fishingGround":0.0455148487512938,"builtupLand":0.0859990156971475,"carbon":0.0497194136122955,"value":1.25066855635538,"score":"3A"},{"id":33965,"version":null,"year":1969,"countryCode":75,"countryName":"Gambia","shortName":"Gambia","isoa2":"GM","record":"EFConsPerCap","cropLand":0.299580197521444,"grazingLand":0.409064393531832,"forestLand":0.24746712763279,"fishingGround":0.0440380832143838,"builtupLand":0.0777729939245687,"carbon":0.0695024296827509,"value":1.14742522550777,"score":"3A"},{"id":33977,"version":null,"year":1970,"countryCode":75,"countryName":"Gambia","shortName":"Gambia","isoa2":"GM","record":"EFConsPerCap","cropLand":0.425408718416882,"grazingLand":0.399919690206316,"forestLand":0.245548846165645,"fishingGround":0.0441281403731244,"builtupLand":0.0782261512267121,"carbon":0.0721131708068078,"value":1.26534471719549,"score":"3A"},{"id":33989,"version":null,"year":1971,"countryCode":75,"countryName":"Gambia","shortName":"Gambia","isoa2":"GM","record":"EFConsPerCap","cropLand":0.531980534001474,"grazingLand":0.387758572078744,"forestLand":0.240084617340274,"fishingGround":0.0439556233832026,"builtupLand":0.082378082740514,"carbon":0.093830640212077,"value":1.37998806975629,"score":"3A"},{"id":34001,"version":null,"year":1972,"countryCode":75,"countryName":"Gambia","shortName":"Gambia","isoa2":"GM","record":"EFConsPerCap","cropLand":0.353286349046365,"grazingLand":0.370306107084308,"forestLand":0.237655938410764,"fishingGround":0.0490209779541788,"builtupLand":0.0762382107392432,"carbon":0.0849837222678372,"value":1.1714913055027,"score":"3A"},{"id":34013,"version":null,"year":1973,"countryCode":75,"countryName":"Gambia","shortName":"Gambia","isoa2":"GM","record":"EFConsPerCap","cropLand":0.554829428404972,"grazingLand":0.365045469842243,"forestLand":0.237220641391001,"fishingGround":0.0774603536570845,"builtupLand":0.0850009170816108,"carbon":0.0973076076568861,"value":1.4168644180338,"score":"3A"},{"id":34025,"version":null,"year":1974,"countryCode":75,"countryName":"Gambia","shortName":"Gambia","isoa2":"GM","record":"EFConsPerCap","cropLand":0.32667362905833,"grazingLand":0.358289584613086,"forestLand":0.227815680220904,"fishingGround":0.0767502759235552,"builtupLand":0.0599813425727529,"carbon":0.0764787039775542,"value":1.12598921636618,"score":"3A"},{"id":34037,"version":null,"year":1975,"countryCode":75,"countryName":"Gambia","shortName":"Gambia","isoa2":"GM","record":"EFConsPerCap","cropLand":0.219602932827685,"grazingLand":0.344252232007262,"forestLand":0.230755403634886,"fishingGround":0.0722565393144533,"builtupLand":0.0587557288982437,"carbon":0.101133618305032,"value":1.02675645498756,"score":"3A"},{"id":34049,"version":null,"year":1976,"countryCode":75,"countryName":"Gambia","shortName":"Gambia","isoa2":"GM","record":"EFConsPerCap","cropLand":0.237084776027513,"grazingLand":0.334817319305184,"forestLand":0.22697044073311,"fishingGround":0.0686218814475125,"builtupLand":0.0630289309182337,"carbon":0.0806824637739802,"value":1.01120581220553,"score":"3A"},{"id":34061,"version":null,"year":1977,"countryCode":75,"countryName":"Gambia","shortName":"Gambia","isoa2":"GM","record":"EFConsPerCap","cropLand":0.150084653376552,"grazingLand":0.32740048974079,"forestLand":0.227793582316467,"fishingGround":0.0977054109041963,"builtupLand":0.0437291427132166,"carbon":0.103269709817246,"value":0.949982988868468,"score":"3A"},{"id":34073,"version":null,"year":1978,"countryCode":75,"countryName":"Gambia","shortName":"Gambia","isoa2":"GM","record":"EFConsPerCap","cropLand":0.515953493210253,"grazingLand":0.319020200852118,"forestLand":0.229932205800093,"fishingGround":0.100080154455953,"builtupLand":0.0573373040842095,"carbon":0.188314637171864,"value":1.41063799557449,"score":"3A"},{"id":34085,"version":null,"year":1979,"countryCode":75,"countryName":"Gambia","shortName":"Gambia","isoa2":"GM","record":"EFConsPerCap","cropLand":0.200887814417955,"grazingLand":0.311028112969645,"forestLand":0.222409420217204,"fishingGround":0.0766935579161783,"builtupLand":0.0350615087871083,"carbon":0.177339191931452,"value":1.02341960623954,"score":"3A"},{"id":34097,"version":null,"year":1980,"countryCode":75,"countryName":"Gambia","shortName":"Gambia","isoa2":"GM","record":"EFConsPerCap","cropLand":0.190427350972574,"grazingLand":0.299956735177831,"forestLand":0.226290040819596,"fishingGround":0.093609330627899,"builtupLand":0.0380637753179785,"carbon":0.194963719721623,"value":1.0433109526375,"score":"3A"},{"id":34109,"version":null,"year":1981,"countryCode":75,"countryName":"Gambia","shortName":"Gambia","isoa2":"GM","record":"EFConsPerCap","cropLand":0.516283184177814,"grazingLand":0.304385467173986,"forestLand":0.222141458233885,"fishingGround":0.12181208960835,"builtupLand":0.0487447812283079,"carbon":0.196665350442816,"value":1.41003233086516,"score":"3A"},{"id":34121,"version":null,"year":1982,"countryCode":75,"countryName":"Gambia","shortName":"Gambia","isoa2":"GM","record":"EFConsPerCap","cropLand":0.614284755054572,"grazingLand":0.286561582001681,"forestLand":0.222938128087371,"fishingGround":0.0584181627403619,"builtupLand":0.0613736443244551,"carbon":0.189969436623513,"value":1.43354570883196,"score":"3A"},{"id":34133,"version":null,"year":1983,"countryCode":75,"countryName":"Gambia","shortName":"Gambia","isoa2":"GM","record":"EFConsPerCap","cropLand":0.286641774024686,"grazingLand":0.276461474577733,"forestLand":0.225252361468735,"fishingGround":0.0695732238724303,"builtupLand":0.0490945712585319,"carbon":0.188583269091972,"value":1.09560667429409,"score":"3A"},{"id":34145,"version":null,"year":1984,"countryCode":75,"countryName":"Gambia","shortName":"Gambia","isoa2":"GM","record":"EFConsPerCap","cropLand":0.396522288079899,"grazingLand":0.262785697949412,"forestLand":0.22133107145439,"fishingGround":0.0761180436936128,"builtupLand":0.0531242313529146,"carbon":0.183278435509233,"value":1.19315976803946,"score":"3A"},{"id":34157,"version":null,"year":1985,"countryCode":75,"countryName":"Gambia","shortName":"Gambia","isoa2":"GM","record":"EFConsPerCap","cropLand":0.421250330119785,"grazingLand":0.25542230209578,"forestLand":0.217947438726156,"fishingGround":0.0630347418441691,"builtupLand":0.0470837346269653,"carbon":0.178703898110817,"value":1.18344244552367,"score":"3A"},{"id":34169,"version":null,"year":1986,"countryCode":75,"countryName":"Gambia","shortName":"Gambia","isoa2":"GM","record":"EFConsPerCap","cropLand":0.512581547239757,"grazingLand":0.242951777250116,"forestLand":0.220944515643213,"fishingGround":0.0618816887261001,"builtupLand":0.0540221226193639,"carbon":0.173135189769888,"value":1.26551684124844,"score":"3A"},{"id":34181,"version":null,"year":1987,"countryCode":75,"countryName":"Gambia","shortName":"Gambia","isoa2":"GM","record":"EFConsPerCap","cropLand":0.572072425672364,"grazingLand":0.25675983665945,"forestLand":0.228117679684718,"fishingGround":0.0764307716673428,"builtupLand":0.054148470627697,"carbon":0.176441516811663,"value":1.36397070112323,"score":"3A"},{"id":34193,"version":null,"year":1988,"countryCode":75,"countryName":"Gambia","shortName":"Gambia","isoa2":"GM","record":"EFConsPerCap","cropLand":0.476142540623321,"grazingLand":0.252287963899775,"forestLand":0.232945469209698,"fishingGround":0.0600371083193482,"builtupLand":0.0411682932211934,"carbon":0.176162643659254,"value":1.23874401893259,"score":"3A"},{"id":34205,"version":null,"year":1989,"countryCode":75,"countryName":"Gambia","shortName":"Gambia","isoa2":"GM","record":"EFConsPerCap","cropLand":0.482114255553021,"grazingLand":0.21001009395514,"forestLand":0.237433871833477,"fishingGround":0.0520268506733375,"builtupLand":0.0592300642312387,"carbon":0.171727714663909,"value":1.21254285091012,"score":"3A"},{"id":34217,"version":null,"year":1990,"countryCode":75,"countryName":"Gambia","shortName":"Gambia","isoa2":"GM","record":"EFConsPerCap","cropLand":0.400661622160234,"grazingLand":0.214467099547665,"forestLand":0.244173628813194,"fishingGround":0.0674028099342939,"builtupLand":0.0401262355338766,"carbon":0.166541138241841,"value":1.1333725342311,"score":"3A"},{"id":34229,"version":null,"year":1991,"countryCode":75,"countryName":"Gambia","shortName":"Gambia","isoa2":"GM","record":"EFConsPerCap","cropLand":0.485054150759098,"grazingLand":0.217381712447165,"forestLand":0.252593694324414,"fishingGround":0.0531588467959956,"builtupLand":0.0431404475311011,"carbon":0.173717322148997,"value":1.22504617400677,"score":"3A"},{"id":34241,"version":null,"year":1992,"countryCode":75,"countryName":"Gambia","shortName":"Gambia","isoa2":"GM","record":"EFConsPerCap","cropLand":0.413602936331461,"grazingLand":0.194522362945923,"forestLand":0.272622795678072,"fishingGround":0.0418949659163803,"builtupLand":0.0397417153451006,"carbon":0.174104019389052,"value":1.13648879560599,"score":"3A"},{"id":34253,"version":null,"year":1993,"countryCode":75,"countryName":"Gambia","shortName":"Gambia","isoa2":"GM","record":"EFConsPerCap","cropLand":0.391167189856545,"grazingLand":0.183429922958156,"forestLand":0.280592942318763,"fishingGround":0.0498133619935739,"builtupLand":0.0460438854284374,"carbon":0.172342942798799,"value":1.12339024535427,"score":"3A"},{"id":34265,"version":null,"year":1994,"countryCode":75,"countryName":"Gambia","shortName":"Gambia","isoa2":"GM","record":"EFConsPerCap","cropLand":0.402475263754554,"grazingLand":0.183957510982393,"forestLand":0.265719945039672,"fishingGround":0.037502757392123,"builtupLand":0.0418445153568291,"carbon":0.181819567847253,"value":1.11331956037282,"score":"3A"},{"id":34277,"version":null,"year":1995,"countryCode":75,"countryName":"Gambia","shortName":"Gambia","isoa2":"GM","record":"EFConsPerCap","cropLand":0.36533531198849,"grazingLand":0.160247507033199,"forestLand":0.261577854986715,"fishingGround":0.057003940369423,"builtupLand":0.0388406101661489,"carbon":0.194698723508856,"value":1.07770394805283,"score":"3A"},{"id":34289,"version":null,"year":1996,"countryCode":75,"countryName":"Gambia","shortName":"Gambia","isoa2":"GM","record":"EFConsPerCap","cropLand":0.319134373178353,"grazingLand":0.156078655651857,"forestLand":0.254352005415086,"fishingGround":0.0543618280368273,"builtupLand":0.0303341063659747,"carbon":0.244393522725965,"value":1.05865449137406,"score":"3A"},{"id":34301,"version":null,"year":1997,"countryCode":75,"countryName":"Gambia","shortName":"Gambia","isoa2":"GM","record":"EFConsPerCap","cropLand":0.435828737320893,"grazingLand":0.147589762026664,"forestLand":0.248604197518153,"fishingGround":0.0588643003174165,"builtupLand":0.0375488657672461,"carbon":0.214943779045977,"value":1.14337964199635,"score":"3A"},{"id":34313,"version":null,"year":1998,"countryCode":75,"countryName":"Gambia","shortName":"Gambia","isoa2":"GM","record":"EFConsPerCap","cropLand":0.373273613877078,"grazingLand":0.143074508222236,"forestLand":0.242636770247586,"fishingGround":0.0406979981752563,"builtupLand":0.0365897221317141,"carbon":0.249331094657975,"value":1.08560370731184,"score":"3A"},{"id":34325,"version":null,"year":1999,"countryCode":75,"countryName":"Gambia","shortName":"Gambia","isoa2":"GM","record":"EFConsPerCap","cropLand":0.550609838794871,"grazingLand":0.118347570726452,"forestLand":0.237541574817618,"fishingGround":0.0570879007864436,"builtupLand":0.0474476246589389,"carbon":0.236797670876628,"value":1.24783218066095,"score":"3A"},{"id":34337,"version":null,"year":2000,"countryCode":75,"countryName":"Gambia","shortName":"Gambia","isoa2":"GM","record":"EFConsPerCap","cropLand":0.518142233790211,"grazingLand":0.101338191116433,"forestLand":0.263275500518809,"fishingGround":0.0451527180146394,"builtupLand":0.0445034498165493,"carbon":0.208000239251721,"value":1.18041233250836,"score":"3A"},{"id":34349,"version":null,"year":2001,"countryCode":75,"countryName":"Gambia","shortName":"Gambia","isoa2":"GM","record":"EFConsPerCap","cropLand":0.475600470362585,"grazingLand":0.0870176746403364,"forestLand":0.257664271465337,"fishingGround":0.0779683422748911,"builtupLand":0.0447318893491198,"carbon":0.185426629061048,"value":1.12840927715332,"score":"3A"},{"id":34361,"version":null,"year":2002,"countryCode":75,"countryName":"Gambia","shortName":"Gambia","isoa2":"GM","record":"EFConsPerCap","cropLand":0.34824381034705,"grazingLand":0.0840784525118793,"forestLand":0.249118651555501,"fishingGround":0.0998765295003597,"builtupLand":0.0298514822177437,"carbon":0.224919205286481,"value":1.03608813141901,"score":"3A"},{"id":34373,"version":null,"year":2003,"countryCode":75,"countryName":"Gambia","shortName":"Gambia","isoa2":"GM","record":"EFConsPerCap","cropLand":0.519488260924176,"grazingLand":0.075507058629777,"forestLand":0.246872118237456,"fishingGround":0.0835715710399753,"builtupLand":0.0358220484506558,"carbon":0.241274087479375,"value":1.20253514476142,"score":"3A"},{"id":34385,"version":null,"year":2004,"countryCode":75,"countryName":"Gambia","shortName":"Gambia","isoa2":"GM","record":"EFConsPerCap","cropLand":0.466726654969232,"grazingLand":0.0795566899891957,"forestLand":0.238341430015681,"fishingGround":0.106972151917584,"builtupLand":0.0435558871760204,"carbon":0.264858939694686,"value":1.2000117537624,"score":"3A"},{"id":34397,"version":null,"year":2005,"countryCode":75,"countryName":"Gambia","shortName":"Gambia","isoa2":"GM","record":"EFConsPerCap","cropLand":0.419976814859221,"grazingLand":0.0744282249092104,"forestLand":0.233009850555966,"fishingGround":0.0872540365809241,"builtupLand":0.0349029062101319,"carbon":0.270361596771904,"value":1.11993342988736,"score":"3A"},{"id":34409,"version":null,"year":2006,"countryCode":75,"countryName":"Gambia","shortName":"Gambia","isoa2":"GM","record":"EFConsPerCap","cropLand":0.402092631238047,"grazingLand":0.0726575116853947,"forestLand":0.228347914067818,"fishingGround":0.103232214610791,"builtupLand":0.0411201605559416,"carbon":0.265768289745741,"value":1.11321872190373,"score":"3A"},{"id":34421,"version":null,"year":2007,"countryCode":75,"countryName":"Gambia","shortName":"Gambia","isoa2":"GM","record":"EFConsPerCap","cropLand":0.47357578091388,"grazingLand":0.062026530082528,"forestLand":0.225828127186546,"fishingGround":0.108911106233755,"builtupLand":0.0271180707416643,"carbon":0.307882551453679,"value":1.20534216661205,"score":"3A"},{"id":34433,"version":null,"year":2008,"countryCode":75,"countryName":"Gambia","shortName":"Gambia","isoa2":"GM","record":"EFConsPerCap","cropLand":0.488563480024837,"grazingLand":0.0607529460835817,"forestLand":0.219938693584615,"fishingGround":0.107225277581395,"builtupLand":0.0330073502957658,"carbon":0.283347816908393,"value":1.19283556447859,"score":"3A"},{"id":34445,"version":null,"year":2009,"countryCode":75,"countryName":"Gambia","shortName":"Gambia","isoa2":"GM","record":"EFConsPerCap","cropLand":0.556784984842724,"grazingLand":0.0595237862926814,"forestLand":0.213863225980442,"fishingGround":0.10625091112417,"builtupLand":0.0344268047633722,"carbon":0.263907590674046,"value":1.23475730367744,"score":"3A"},{"id":34457,"version":null,"year":2010,"countryCode":75,"countryName":"Gambia","shortName":"Gambia","isoa2":"GM","record":"EFConsPerCap","cropLand":0.693583203757741,"grazingLand":0.068129352994631,"forestLand":0.212032498867517,"fishingGround":0.106784150452506,"builtupLand":0.036191543888186,"carbon":0.242324801745856,"value":1.35904555170644,"score":"3A"},{"id":34469,"version":null,"year":2011,"countryCode":75,"countryName":"Gambia","shortName":"Gambia","isoa2":"GM","record":"EFConsPerCap","cropLand":0.435362257760192,"grazingLand":0.0602353404380051,"forestLand":0.207329472364316,"fishingGround":0.0914718882778793,"builtupLand":0.0212038182802935,"carbon":0.247249423242889,"value":1.06285220036358,"score":"3A"},{"id":34481,"version":null,"year":2012,"countryCode":75,"countryName":"Gambia","shortName":"Gambia","isoa2":"GM","record":"EFConsPerCap","cropLand":0.483317624384292,"grazingLand":0.0516800327124025,"forestLand":0.20210479164583,"fishingGround":0.0780635706117065,"builtupLand":0.027501376283798,"carbon":0.156842239239328,"value":0.999509634877357,"score":"3A"},{"id":34493,"version":null,"year":2013,"countryCode":75,"countryName":"Gambia","shortName":"Gambia","isoa2":"GM","record":"EFConsPerCap","cropLand":0.402828128602824,"grazingLand":0.0450955566403863,"forestLand":0.200282838780732,"fishingGround":0.0878014325421523,"builtupLand":0.0237997701700746,"carbon":0.172819387414906,"value":0.932627114151074,"score":"3A"},{"id":34505,"version":null,"year":2014,"countryCode":75,"countryName":"Gambia","shortName":"Gambia","isoa2":"GM","record":"EFConsPerCap","cropLand":0.407783383729383,"grazingLand":0.0625242686603761,"forestLand":0.198271640775846,"fishingGround":0.101899290993343,"builtupLand":0.0199773126774348,"carbon":0.243782292881866,"value":1.03423818971825,"score":"3A"},{"id":34517,"version":null,"year":2015,"countryCode":75,"countryName":"Gambia","shortName":"Gambia","isoa2":"GM","record":"EFConsPerCap","cropLand":0.434885446310678,"grazingLand":0.0824532518262002,"forestLand":0.191696859331344,"fishingGround":0.112966289449475,"builtupLand":0.0242550467033379,"carbon":0.268858355275173,"value":1.11511524889621,"score":"3A"},{"id":34529,"version":null,"year":2016,"countryCode":75,"countryName":"Gambia","shortName":"Gambia","isoa2":"GM","record":"EFConsPerCap","cropLand":0.374031231329896,"grazingLand":0.0498327970726021,"forestLand":0.161204911782331,"fishingGround":0.115670251381902,"builtupLand":0.0271097458012577,"carbon":0.274937881727664,"value":1.00278681909565,"score":"3A"}]